markdown_format_ruff/__init__.py
markdown_format_ruff/py.typed
markdown_format_ruff-1.0.0.dist-info/METADATA
markdown_format_ruff-1.0.0.dist-info/WHEEL
markdown_format_ruff-1.0.0.dist-info/entry_points.txt
markdown_format_ruff-1.0.0.dist-info/licenses/LICENSE
markdown_format_ruff-1.0.0.dist-info/RECORD
