Metadata-Version: 2.4
Name: markdown-format-ruff
Version: 1.0.0
Summary: Mdformat plugin to run ruff on Python code blocks.
Author-email: Bagard Hoel <hoel.bagard.hy@hitachi-hightech.com>
License-File: LICENSE
Requires-Python: >=3.7
Requires-Dist: ruff
